{
  "panel": {
    "calendar": "التقويم",
    "config": "الإعدادات",
    "states": "نظرة عامة",
    "map": "خريطة",
    "logbook": "سجل",
    "history": "التاريخ",
    "mailbox": "البريد",
    "shopping_list": "قائمة التسوق",
    "developer_tools": "ادوات المطورين",
    "media_browser": "Media Browser",
    "profile": "الملف الشخصي"
  },
  "state": {
    "default": {
      "on": "مشغل",
      "off": "مطفئ",
      "unknown": "غير معروف",
      "unavailable": "غير متوفر"
    },
    "alarm_control_panel": {
      "armed": "مسلح",
      "armed_away": "مفعّل في الخارج",
      "armed_custom_bypass": "تجاوز التفعيل",
      "armed_home": "مفعّل في المنزل",
      "armed_night": "مفعّل ليل",
      "arming": "جاري التفعيل",
      "disarmed": "غير مفعّل",
      "disarming": "إيقاف الإنذار",
      "pending": "قيد الإنتظار",
      "triggered": "مفعّل"
    },
    "automation": { "off": "إيقاف", "on": "تشغيل" },
    "binary_sensor": {
      "battery": { "off": "طبيعي", "on": "منخفض" },
      "cold": { "off": "طبيعي", "on": "بارد" },
      "connectivity": { "off": "مفصول", "on": "متصل" },
      "default": { "off": "إيقاف", "on": "تشغيل" },
      "door": { "off": "مغلق", "on": "مفتوح" },
      "garage_door": { "off": "مغلق", "on": "مفتوح" },
      "gas": { "off": "لم يتم الكشف", "on": "تم الكشف" },
      "heat": { "off": "طبيعي", "on": "حار" },
      "lock": { "off": "مقفل", "on": "غير مقفل" },
      "moisture": { "off": "جاف", "on": "مبلل" },
      "motion": { "off": "لم يتم الكشف", "on": "تم الكشف" },
      "occupancy": { "off": "لم يتم الكشف", "on": "تم الكشف" },
      "opening": { "off": "مقفل", "on": "مفتوح" },
      "presence": { "off": "خارج المنزل", "on": "في المنزل" },
      "problem": { "off": "موافق", "on": "عطل" },
      "safety": { "off": "أمن", "on": "غير أمن" },
      "smoke": { "off": "لم يتم الكشف", "on": "تم الكشف" },
      "sound": { "off": "لم يتم الكشف", "on": "تم الكشف" },
      "vibration": { "off": "لم يتم الكشف", "on": "تم الكشف" },
      "window": { "off": "مغلق", "on": "مفتوح" }
    },
    "calendar": { "off": "إيقاف", "on": "تشغيل" },
    "camera": {
      "idle": "خامل",
      "recording": "جاري التسجيل",
      "streaming": "جاري البث"
    },
    "climate": {
      "cool": "تبريد",
      "dry": "جاف",
      "fan_only": "المروحة فقط",
      "heat": "تدفئة",
      "off": "إيقاف"
    },
    "configurator": { "configure": "إعداد", "configured": "تم التكوين" },
    "cover": {
      "closed": "مغلق",
      "closing": "جاري الاغلاق",
      "open": "مفتوح",
      "opening": "جاري الفتح",
      "stopped": "موقف"
    },
    "device_tracker": { "not_home": "خارج المنزل" },
    "fan": { "off": "إيقاف", "on": "قيد التشغيل" },
    "group": {
      "closed": "مغلق ",
      "closing": "جاري الاغلاق ",
      "home": "في المنزل",
      "locked": "مقفل ",
      "not_home": "في الخارج",
      "off": "إيقاف",
      "ok": "أوكي",
      "on": "تشغيل",
      "open": "مفتوح ",
      "opening": "جاري الفتح ",
      "problem": "مشكلة",
      "stopped": "موقف ",
      "unlocked": "غير مقفل "
    },
    "input_boolean": { "off": "إيقاف", "on": "تشغيل" },
    "light": { "off": "إيقاف", "on": "تشغيل" },
    "lock": { "locked": "مقفل", "unlocked": "مفتوح" },
    "media_player": {
      "idle": "خامل",
      "off": "إيقاف",
      "on": "قيد التشغيل",
      "paused": "موقّف مؤقتا",
      "playing": "جاري التشغيل",
      "standby": "وضع الإنتظار"
    },
    "person": { "home": "في المنزل" },
    "plant": { "ok": "أوكي", "problem": "مشكلة" },
    "remote": { "off": "إيقاف", "on": "قيد التشغيل" },
    "scene": { "scening": "تشهيد" },
    "script": { "off": "إيقاف", "on": "قيد التشغيل" },
    "sensor": { "off": "إيقاف", "on": "قيد التشغيل" },
    "sun": { "above_horizon": "فوق الأفق", "below_horizon": "تحت الأفق" },
    "switch": { "off": "إيقاف", "on": "تشغيل" },
    "timer": { "active": "مفعل", "idle": "خامل", "paused": "موقّف مؤقتا" },
    "vacuum": {
      "cleaning": "تنظيف",
      "error": "خطأ",
      "off": "مطفئ",
      "on": "مشغل",
      "paused": "موقّف مؤقتا",
      "returning": "العودة"
    },
    "weather": {
      "clear-night": "صافي، ليلا",
      "cloudy": "Bewolkt",
      "fog": "Mist",
      "lightning": "برق",
      "lightning-rainy": "برق ، ممطر",
      "partlycloudy": "غائم جزئيا",
      "pouring": "أمطار غزيرة",
      "rainy": "ماطر",
      "snowy": "ثلوج",
      "snowy-rainy": "ثلوج، ماطر",
      "sunny": "مشمس",
      "windy": "عاصف",
      "windy-variant": "عاصف"
    },
    "zwave": {
      "default": {
        "dead": "مفصول",
        "initializing": "قيد الإنشاء",
        "ready": "جاهز",
        "sleeping": "نائم"
      },
      "query_stage": {
        "dead": "مفصول ({query_stage})",
        "initializing": "قيد الإنشاء ( {query_stage} )"
      }
    }
  },
  "state_attributes": {
    "climate": {
      "fan_mode": { "off": "إيقاف", "on": "تشغيل", "auto": "تلقائي" },
      "preset_mode": {
        "none": "None",
        "eco": "Eco",
        "away": "Away",
        "boost": "Boost",
        "comfort": "Comfort",
        "home": "Home",
        "sleep": "Sleep",
        "activity": "Activity"
      },
      "hvac_action": {
        "off": "Off",
        "heating": "Heating",
        "cooling": "Cooling",
        "drying": "تجفيف",
        "idle": "Idle",
        "fan": "Fan"
      }
    },
    "humidifier": {
      "mode": {
        "normal": "عادي",
        "eco": "اقتصادي",
        "away": "Away",
        "boost": "Boost",
        "comfort": "الراحة",
        "home": "في المنزل",
        "sleep": "Sleep",
        "auto": "تلقائي",
        "baby": "الطفل"
      }
    }
  },
  "state_badge": {
    "default": {
      "unknown": "غير معروف",
      "unavailable": "غير متوفر",
      "error": "Error",
      "entity_not_found": "Entity Not Found"
    },
    "alarm_control_panel": {
      "armed": "مفعل",
      "disarmed": "غير مفعّل",
      "armed_home": "مفعّل",
      "armed_away": "مفعّل",
      "armed_night": "مفعل",
      "armed_custom_bypass": "مفعّل",
      "pending": "إنتظار",
      "arming": "جاري التفعيل",
      "disarming": "إيقاف الإنذار",
      "triggered": "مفعّل"
    },
    "device_tracker": { "home": "في المنزل", "not_home": "خارج المنزل" },
    "person": { "home": "في المنزل", "not_home": "خارج المنزل" }
  },
  "groups": {
    "system-admin": "مسؤولين",
    "system-users": "مستخدمين",
    "system-read-only": "مستخدمين للعرض فقط"
  },
  "config_entry": {
    "disabled_by": {
      "user": "User",
      "integration": "تكامل",
      "config_entry": "Config Entry"
    }
  },
  "ui": {
    "auth_store": {
      "ask": "هل تريد حفظ هذا الدخول؟",
      "decline": "لا شكرا",
      "confirm": "نعم"
    },
    "card": {
      "alarm_control_panel": {
        "code": "الرمز",
        "clear_code": "مسح",
        "disarm": "تعطيل",
        "arm_home": "تفعيل في المنزل",
        "arm_away": "تفعيل خارج المنزل",
        "arm_night": "Arm night",
        "arm_custom_bypass": "تجاوز مخصص"
      },
      "automation": { "last_triggered": "آخر تشغيل", "trigger": "تشغيل" },
      "camera": { "not_available": "الصورة غير متاحة" },
      "climate": {
        "currently": "حاليا",
        "on_off": "إيقاف/تشغيل",
        "target_temperature": "درجة الحرارة المستهدفة",
        "target_temperature_entity": "{name} target temperature",
        "target_temperature_mode": "{name} target temperature {mode}",
        "current_temperature": "{name} current temperature",
        "heating": "{name} heating",
        "cooling": "{name} cooling",
        "high": "high",
        "low": "low",
        "target_humidity": "Doelluchtvochtigheid",
        "operation": "Operation",
        "fan_mode": "وضع المروحة",
        "swing_mode": "Swing mode",
        "preset_mode": "Preset",
        "away_mode": "خارج المنزل",
        "aux_heat": "Aux heat"
      },
      "counter": {
        "actions": {
          "increment": "increment",
          "decrement": "decrement",
          "reset": "reset"
        }
      },
      "cover": { "position": "Position", "tilt_position": "Tilt position" },
      "fan": {
        "speed": "Snelheid",
        "oscillate": "Oscillate",
        "direction": "Richting",
        "forward": "Forward",
        "reverse": "Reverse"
      },
      "humidifier": {
        "humidity": "الرطوبة المستهدفة",
        "mode": "الوضع",
        "target_humidity_entity": "{name} الرطوبة المستهدفة",
        "on_entity": "{name} on"
      },
      "light": {
        "brightness": "Helderheid",
        "color_temperature": "Kleurtemperatuur",
        "white_value": "قيمة البياض",
        "effect": "Effect"
      },
      "lock": { "code": "Code", "lock": "قفل", "unlock": "فتح" },
      "media_player": {
        "source": "المصدر",
        "sound_mode": "وضع الصوت",
        "browse_media": "Browse media",
        "turn_on": "Turn on",
        "turn_off": "Turn off",
        "media_play": "Play",
        "media_play_pause": "Play/pause",
        "media_next_track": "Next",
        "media_previous_track": "Previous",
        "text_to_speak": "النص للتحدث"
      },
      "persistent_notification": { "dismiss": "رفض" },
      "scene": { "activate": "تفعيل" },
      "script": {
        "execute": "نفذ",
        "cancel": "إلغاء",
        "cancel_multiple": "إلغاء {number}"
      },
      "service": { "run": "تشغيل" },
      "timer": {
        "actions": {
          "start": "start",
          "pause": "pause",
          "cancel": "cancel",
          "finish": "finish"
        }
      },
      "vacuum": {
        "actions": {
          "resume_cleaning": "استئناف التنظيف",
          "return_to_base": "العودة",
          "start_cleaning": "بدء تنظيف",
          "turn_on": "تشغيل",
          "turn_off": "إيقاف"
        }
      },
      "water_heater": {
        "currently": "حاليا",
        "on_off": "إيقاف/تشغيل",
        "target_temperature": "درجة الحرارة المستهدفة",
        "operation": "تشغيل",
        "away_mode": "حالة خارج المنزل"
      },
      "weather": {
        "attributes": {
          "air_pressure": "الضغط الجوي",
          "humidity": "الرطوبة",
          "temperature": "الحرارة",
          "visibility": "الرؤية",
          "wind_speed": "سرعة الرياح",
          "precipitation": "ترسب"
        },
        "cardinal_direction": {
          "e": "E",
          "ene": "ENE",
          "ese": "ESE",
          "n": "N",
          "ne": "NE",
          "nne": "NNE",
          "nw": "NW",
          "nnw": "NNW",
          "s": "S",
          "se": "SE",
          "sse": "SSE",
          "ssw": "SSW",
          "sw": "SW",
          "w": "W",
          "wnw": "WNW",
          "wsw": "WSW"
        },
        "day": "Day",
        "night": "Night",
        "forecast": "التوقعات",
        "high": "عالي",
        "low": "منخفض"
      }
    },
    "common": {
      "and": "و",
      "continue": "Continue",
      "previous": "السابق",
      "loading": "جار التحميل",
      "refresh": "تحديث",
      "cancel": "إلغاء",
      "delete": "حذف",
      "remove": "Remove",
      "enable": "Enable",
      "disable": "Disable",
      "close": "Close",
      "leave": "Leave",
      "stay": "Stay",
      "next": "التالى",
      "back": "عودة",
      "undo": "تراجع",
      "save": "Save",
      "rename": "Rename",
      "yes": "Yes",
      "no": "No",
      "not_now": "Not now",
      "skip": "Skip",
      "menu": "القائمه",
      "overflow_menu": "قائمة تجاوز السعة",
      "successfully_saved": "Successfully saved",
      "successfully_deleted": "تم الحذف بنجاح",
      "error_required": "مطلوب",
      "copied": "Copied"
    },
    "components": {
      "logbook": {
        "entries_not_found": "No logbook entries found.",
        "by": "by",
        "by_service": "by service",
        "messages": {
          "was_away": "was away",
          "was_at_state": "was at {state}",
          "rose": "rose",
          "set": "set",
          "was_low": "was low",
          "was_normal": "was normal",
          "was_connected": "was connected",
          "was_disconnected": "was disconnected",
          "was_opened": "was opened",
          "was_closed": "was closed",
          "was_unlocked": "was unlocked",
          "was_locked": "was locked",
          "was_plugged_in": "was plugged in",
          "was_unplugged": "was unplugged",
          "was_at_home": "was at home",
          "was_unsafe": "was unsafe",
          "was_safe": "was safe",
          "detected_device_class": "detected {device_class}",
          "cleared_device_class": "cleared (no {device_class} detected)",
          "turned_off": "turned off",
          "turned_on": "turned on",
          "changed_to_state": "changed to {state}",
          "became_unavailable": "became unavailable"
        }
      },
      "entity": {
        "entity-picker": {
          "entity": "الجهاز",
          "clear": "Clear",
          "show_entities": "Show entities"
        },
        "entity-attribute-picker": {
          "attribute": "Attribute",
          "show_attributes": "Show attributes"
        }
      },
      "user-picker": {
        "no_user": "No user",
        "add_user": "Add user",
        "remove_user": "Remove user"
      },
      "device-picker": {
        "clear": "Clear",
        "toggle": "تبديل",
        "show_devices": "Show devices",
        "device": "Device",
        "no_area": "لا مجال"
      },
      "area-picker": {
        "clear": "مسح",
        "show_areas": "إظهار المناطق",
        "area": "المنطقة",
        "add_new": "إضافة منطقة جديدة ...",
        "add_dialog": {
          "title": "أضف منطقة جديدة",
          "text": "أدخل اسم المنطقة الجديدة.",
          "name": "الاسم",
          "add": "إضافة",
          "failed_create_area": "Failed to create area."
        }
      },
      "picture-upload": {
        "label": "Picture",
        "unsupported_format": "Unsupported format, please choose a JPEG, PNG or GIF image."
      },
      "date-range-picker": {
        "start_date": "تاريخ البدء",
        "end_date": "تاريخ الإنتهاء",
        "select": "Select"
      },
      "relative_time": {
        "never": "Nooit",
        "just_now": "Just now",
        "duration": {
          "second": "{count} {count, plural,\n  one {second}\n  other {seconds}\n}",
          "minute": "{count} {count, plural,\n  one {دقيقة}\n  other {دقائق}\n}",
          "hour": "{count} {count, plural,\none {ساعة}\nother {ساعات}\n}",
          "day": "{count} {count, plural,\n  one {day}\n  other {days}\n}",
          "week": "{count} {count, plural,\n  one {week}\n  other {weeks}\n}"
        },
        "past_duration": {
          "second": "{count} {count, plural,\n  one {second}\n  other {seconds}\n} ago",
          "minute": "{count} {count, plural,\n  one {minute}\n  other {minutes}\n} ago",
          "hour": "{count} {count, plural,\n  one {hour}\n  other {hours}\n} ago",
          "day": "{count} {count, plural,\n  one {day}\n  other {days}\n} ago",
          "week": "{count} {count, plural,\n  one {week}\n  other {weeks}\n} ago"
        },
        "future_duration": {
          "second": "In {count} {count, plural,\n  one {second}\n  other {seconds}\n}",
          "minute": "In {count} {count, plural,\n  one {minute}\n  other {minutes}\n}",
          "hour": "In {count} {count, plural,\n  one {hour}\n  other {hours}\n}",
          "day": "In {count} {count, plural,\n  one {day}\n  other {days}\n}",
          "week": "In {count} {count, plural,\n  one {week}\n  other {weeks}\n}"
        },
        "future": "قبل {time}"
      },
      "history_charts": {
        "loading_history": "جارٍ تحميل سجل الحالات ...",
        "no_history_found": "لم يتم العثور على سجل الحالات."
      },
      "service-picker": { "service": "خدمة" },
      "related-items": {
        "no_related_found": "No related items found.",
        "integration": "تكامل",
        "device": "Device",
        "area": "Area",
        "entity": "Related entities",
        "group": "Part of the following groups",
        "scene": "Part of the following scenes",
        "script": "Part of the following scripts",
        "automation": "Part of the following automations"
      },
      "data-table": { "search": "بحث", "no-data": "لايوجد بيانات" },
      "media-browser": {
        "pick": "Pick",
        "play": "Play",
        "play-media": "Play Media",
        "pick-media": "Pick Media",
        "no_items": "No items",
        "choose_player": "Choose Player",
        "media-player-browser": "Media Player Browser",
        "web-browser": "Web Browser",
        "media_player": "Media Player",
        "audio_not_supported": "Your browser does not support the audio element.",
        "video_not_supported": "Your browser does not support the video element.",
        "media_not_supported": "The Browser Media Player does not support this type of media",
        "media_browsing_error": "Media Browsing Error",
        "learn_adding_local_media": "Learn more about adding media in the {documentation}.",
        "local_media_files": "Place your video, audio and image files in the media directory to be able to browse and play them in the browser or on supported media players.",
        "documentation": "documentation",
        "no_local_media_found": "No local media found",
        "no_media_folder": "It looks like you have not yet created a media directory.",
        "setup_local_help": "Check the {documentation} on how to setup local media.",
        "class": {
          "album": "Album",
          "app": "App",
          "artist": "Artist",
          "channel": "Channel",
          "composer": "Composer",
          "contributing_artist": "Contributing Artist",
          "directory": "Library",
          "episode": "Episode",
          "game": "Game",
          "genre": "Genre",
          "image": "Image",
          "movie": "Movie",
          "music": "Music",
          "playlist": "Playlist",
          "podcast": "Podcast",
          "season": "Season",
          "track": "Track",
          "tv_show": "TV Show",
          "url": "URL",
          "video": "Video"
        }
      }
    },
    "dialogs": {
      "quick-bar": {
        "commands": {
          "reload": {
            "reload": "Reload {domain}",
            "core": "Reload location & customizations",
            "group": "Reload groups, group entities, and notify services",
            "automation": "Reload automations",
            "script": "Reload scripts",
            "scene": "Reload scenes",
            "person": "Reload people",
            "zone": "Reload zones",
            "input_boolean": "Reload input booleans",
            "input_text": "Reload input texts",
            "input_number": "Reload input numbers",
            "input_datetime": "Reload input date times",
            "input_select": "Reload input selects",
            "template": "Reload template entities",
            "universal": "Reload universal media player entities",
            "rest": "Reload rest entities and notify services",
            "command_line": "Reload command line entities",
            "filter": "Reload filter entities",
            "statistics": "Reload statistics entities",
            "generic": "Reload generic IP camera entities",
            "generic_thermostat": "Reload generic thermostat entities",
            "homekit": "Reload HomeKit",
            "min_max": "Reload min/max entities",
            "history_stats": "Reload history stats entities",
            "trend": "Reload trend entities",
            "ping": "Reload ping binary sensor entities",
            "filesize": "Reload file size entities",
            "telegram": "Reload telegram notify services",
            "smtp": "Reload SMTP notify services",
            "mqtt": "Reload manually configured MQTT entities",
            "rpi_gpio": "Reload Raspberry Pi GPIO entities"
          },
          "server_control": {
            "perform_action": "{action} Server",
            "restart": "Restart",
            "stop": "Stop"
          },
          "navigation": {
            "navigate_to": "Navigate to {panel}",
            "navigate_to_config": "Navigate to {panel} configuration",
            "logs": "Logs",
            "automation": "Automations",
            "script": "Scripts",
            "integrations": "Integrations",
            "areas": "Areas",
            "scene": "Scenes",
            "helpers": "Helpers",
            "tags": "Tags",
            "person": "People",
            "devices": "Devices",
            "entities": "Entities",
            "lovelace": "Lovelace Dashboards",
            "core": "General",
            "zone": "Zones",
            "users": "Users",
            "info": "Info",
            "customize": "Customizations",
            "server_control": "Server Controls"
          }
        },
        "filter_placeholder": "Entity Filter"
      },
      "voice_command": {
        "did_not_hear": "Home Assistant لم يسمع أي شيء",
        "found": "I found the following for you:",
        "error": "Oops, an error has occurred",
        "how_can_i_help": "How can I help?",
        "label": "Type a question and press 'Enter'",
        "label_voice": "Type and press 'Enter' or tap the microphone to speak"
      },
      "generic": {
        "cancel": "إلغاء الأمر",
        "ok": "موافق",
        "default_confirmation_title": "هل أنت متأكد؟",
        "close": "إغلاق"
      },
      "image_cropper": { "crop": "Crop" },
      "more_info_control": {
        "dismiss": "Dismiss dialog",
        "settings": "Entity settings",
        "edit": "Edit entity",
        "details": "Details",
        "history": "History",
        "last_changed": "Last changed",
        "last_updated": "Last updated",
        "script": {
          "last_action": "Last Action",
          "last_triggered": "Last Triggered"
        },
        "sun": {
          "elevation": "Elevation",
          "rising": "Rising",
          "setting": "ضبط"
        },
        "updater": { "title": "Update Instructions" },
        "restored": {
          "not_provided": "This entity is currently unavailable and is an orphan to a removed, changed or dysfunctional integration or device.",
          "remove_intro": "If the entity is no longer in use, you can clean it up by removing it.",
          "remove_action": "Remove entity",
          "confirm_remove_title": "Remove entity?",
          "confirm_remove_text": "Are you sure you want to remove this entity?"
        },
        "vacuum": {
          "status": "الحالة",
          "commands": "Vacuum cleaner commands:",
          "fan_speed": "سرعة المروحة",
          "start": "بدء",
          "pause": "إيقاف مؤقت",
          "stop": "توقف",
          "clean_spot": "Clean spot",
          "locate": "Locate",
          "return_home": "العودة للرئيسية",
          "start_pause": "بدء/إيقاف مؤقت"
        },
        "person": { "create_zone": "Create zone from current location" },
        "cover": {
          "open_tilt_cover": "Open cover tilt",
          "close_tile_cover": "Close cover tilt",
          "stop_cover": "Stop cover from moving"
        }
      },
      "entity_registry": {
        "settings": "Settings",
        "control": "Control",
        "related": "ذات صلة",
        "dismiss": "Dismiss",
        "no_unique_id": "This entity does not have a unique ID, therefore its settings cannot be managed from the UI. See the {faq_link} for more detail.",
        "faq": "documentation",
        "editor": {
          "name": "Name",
          "icon": "Icon",
          "icon_error": "Icons should be in the format 'prefix:iconname', e.g. 'mdi:home'",
          "entity_id": "Entity ID",
          "unavailable": "This entity is not currently available.",
          "enabled_label": "Enable entity",
          "enabled_cause": "Disabled by {cause}.",
          "enabled_description": "Disabled entities will not be added to Home Assistant.",
          "enabled_delay_confirm": "The enabled entities will be added to Home Assistant in {delay} seconds",
          "enabled_restart_confirm": "Restart Home Assistant to finish enabling the entities",
          "delete": "حذف",
          "confirm_delete": "هل أنت متأكد أنك تريد حذف هذا الإدخال؟",
          "update": "تحديث",
          "note": "ملاحظة: قد لا يعمل مع كافة التكاملات بعد."
        }
      },
      "helper_settings": {
        "platform_not_loaded": "لم يتم تحميل تكامل {platform} . يرجى إضافته إلى التكوين الخاص بك إما عن طريق إضافة ':default_config' أو \"{platform}\".",
        "yaml_not_editable": "The settings of this entity cannot be edited from the UI. Only entities set up from the UI are configurable from the UI.",
        "required_error_msg": "This field is required",
        "generic": { "name": "Name", "icon": "أيقونة" },
        "input_datetime": {
          "date": "تاريخ",
          "time": "الوقت",
          "datetime": "التاريخ والوقت",
          "mode": "ما الذي تريد إدخاله"
        },
        "input_text": {
          "min": "الحد الأدنى للطول",
          "max": "الحد الأقصى للطول",
          "mode": "Display mode",
          "text": "Text",
          "password": "كلمة المرور",
          "pattern": "Regex pattern for client-side validation"
        },
        "input_number": {
          "min": "Minimum value",
          "max": "Maximum value",
          "mode": "Display mode",
          "box": "Input field",
          "slider": "Slider",
          "step": "Step size",
          "unit_of_measurement": "Unit of measurement"
        },
        "input_select": {
          "options": "Options",
          "add_option": "Add option",
          "no_options": "There are no options yet.",
          "add": "إضافة"
        },
        "counter": {
          "minimum": "Minimum value",
          "maximum": "Maximum value",
          "initial": "Initial value",
          "restore": "Restore the last known value when Home Assistant starts",
          "step": "Step size"
        },
        "timer": { "duration": "Duration" }
      },
      "options_flow": {
        "form": { "header": "Options" },
        "success": { "description": "Options successfully saved." }
      },
      "config_entry_system_options": {
        "title": "خيارات النظام لـ {integration}",
        "enable_new_entities_label": "Enable newly added entities.",
        "enable_new_entities_description": "إذا تم تعطيله ، فلن تتم إضافة الكيانات المكتشفة حديثًا لـ {integration} تلقائيًا إلى Home Assistant.",
        "update": "تحديث"
      },
      "zha_device_info": {
        "manuf": "by {manufacturer}",
        "no_area": "No Area",
        "device_signature": "توقيع جهاز Zigbee",
        "buttons": {
          "add": "أضف أجهزة عبر هذا الجهاز",
          "remove": "Remove Device",
          "clusters": "إدارة العناقيد",
          "reconfigure": "Reconfigure Device",
          "zigbee_information": "معلومات جهاز Zigbee"
        },
        "services": {
          "reconfigure": "Reconfigure ZHA device (heal device). Use this if you are having issues with the device. If the device in question is a battery powered device please ensure it is awake and accepting commands when you use this service.",
          "updateDeviceName": "Set a custom name for this device in the device registry.",
          "remove": "Remove a device from the Zigbee network.",
          "zigbee_information": "عرض معلومات Zigbee للجهاز."
        },
        "confirmations": {
          "remove": "Are you sure that you want to remove the device?"
        },
        "quirk": "Quirk",
        "last_seen": "Last Seen",
        "power_source": "Power Source",
        "unknown": "Unknown",
        "zha_device_card": { "device_name_placeholder": "تغيير اسم الجهاز" }
      },
      "domain_toggler": {
        "title": "Toggle Domains",
        "reset_entities": "Reset Entities"
      },
      "mqtt_device_debug_info": {
        "title": "{device} معلومات تصحيح الأخطاء",
        "deserialize": "محاولة تحليل رسائل MQTT كJSON",
        "entities": "الكيانات",
        "no_entities": "لا توجد كيانات",
        "no_triggers": "لا توجد محفزات",
        "payload_display": "عرض الـPayload",
        "recent_messages": "{n} آخر الرسائل التي تم استلامها",
        "show_as_yaml": "إظهار كـ YAML",
        "triggers": "محفزات"
      }
    },
    "duration": {
      "second": "{count} {count, plural,\none {ثانية}\nother {ثواني}\n}",
      "minute": "{count} {count, plural,\n  one {minute}\n  other {minutes}\n}",
      "hour": "{count} {count, plural,\n  one {hour}\n  other {hours}\n}",
      "day": "{count} {count, plural,\none {يوم}\nother {أيام}\n}",
      "week": "{count} {count, plural,\none {أسبوع}\nother {أسابيع}\n}"
    },
    "login-form": {
      "password": "كلمة السر",
      "remember": "تذكر",
      "log_in": "تسجيل الدخول"
    },
    "notification_drawer": {
      "click_to_configure": "انقر هنا لتعديل {entity}",
      "empty": "لا إشعارات",
      "title": "إشعارات",
      "close": "Close",
      "dismiss_all": "Dismiss all"
    },
    "notification_toast": {
      "service_call_failed": "Failed to call service {service}.",
      "connection_lost": "انقطع الاتصال. جارٍ إعادة الاتصال ...",
      "started": "Home Assistant بدأ!",
      "starting": "يبدأ برنامج Home Assistant حاليا ، ولن يكون كل شيء متاحًا حتى الانتهاء.",
      "triggered": "Triggered {name}",
      "dismiss": "Dismiss"
    },
    "sidebar": {
      "external_app_configuration": "App Configuration",
      "sidebar_toggle": "Sidebar Toggle",
      "done": "Done"
    },
    "panel": {
      "calendar": { "my_calendars": "تقاويمي", "today": "اليوم" },
      "lovelace": {
        "cards": {
          "confirm_delete": "Are you sure you want to delete this card?",
          "empty_state": {
            "title": "Welcome Home",
            "no_devices": "تسمح لك هذه الصفحة بالتحكم في أجهزتك ، ولكن يبدو أنك لم تعد أي أجهزة حتى الآن. توجه إلى صفحة التكاملات للبدء.",
            "go_to_integrations_page": "انتقل إلى صفحة التكاملات."
          },
          "entities": { "never_triggered": "Never triggered" },
          "shopping-list": {
            "checked_items": "Checked items",
            "clear_items": "Clear checked items",
            "add_item": "Add item"
          },
          "picture-elements": {
            "hold": "Hold:",
            "tap": "Tap:",
            "navigate_to": "Navigate to {location}",
            "url": "Open window to {url_path}",
            "toggle": "Toggle {name}",
            "call_service": "Call service {name}",
            "more_info": "Show more-info: {name}"
          },
          "safe-mode": {
            "header": "Safe Mode Activated",
            "description": "واجه Home Assistant مشكلة أثناء تحميل التكوينات الخاصة بك ويتم تشغيله الآن في الوضع الآمن. أنظر إلى سجل الأخطاء لمعرفة  الخطأ."
          },
          "starting": {
            "description": "Home Assistant يبدأ، يرجى الانتظار...",
            "header": "Home Assistant يبدأ..."
          }
        },
        "unused_entities": {
          "title": "Unused entities",
          "available_entities": "These are the entities that you have available, but are not in your Lovelace UI yet.",
          "select_to_add": "Select the entities you want to add to a card and then click the add card button.",
          "entity": "Entity",
          "entity_id": "Entity ID",
          "domain": "Domain",
          "last_changed": "Last Changed",
          "search": "إبحث عن الكيانات",
          "no_data": "لم يعثر على كيانات غير مستخدمة"
        },
        "add_entities": {
          "yaml_unsupported": "You cannot use this function when using Lovelace UI in YAML mode.",
          "generated_unsupported": "You can only use this function when you have taken control of the Lovelace UI.",
          "saving_failed": "Saving Lovelace UI configuration failed."
        },
        "views": {
          "confirm_delete": "Delete view?",
          "confirm_delete_text": "هل أنت متأكد من أنك تريد حذف عرض \"{name}\" ؟",
          "confirm_delete_existing_cards": "سيؤدي حذف هذا العرض إلى إزالة البطاقات أيضًا",
          "confirm_delete_existing_cards_text": "هل أنت متأكد من أنك تريد حذف طريقة عرض ''{name}''؟ تحتوي طريقة العرض على {number} بطاقات سيتم حذفها. لا يمكن التراجع عن هذا الإجراء."
        },
        "menu": {
          "configure_ui": "Edit Dashboard",
          "help": "Help",
          "start_conversation": "Start conversation",
          "reload_resources": "إعادة تحميل الموارد",
          "exit_edit_mode": "Exit UI edit mode",
          "close": "Close"
        },
        "reload_resources": {
          "refresh_header": "هل تريد التحديث؟",
          "refresh_body": "يجب عليك تحديث الصفحة لإكمال إعادة التحميل ، هل تريد التحديث الآن؟"
        },
        "editor": {
          "header": "Edit UI",
          "menu": {
            "open": "Open Lovelace UI menu",
            "raw_editor": "Raw configuration editor"
          },
          "common": {
            "edit": "Edit",
            "clear": "Clear",
            "add": "Add",
            "none": "None"
          },
          "raw_editor": {
            "header": "تعديل",
            "save": "حفظ",
            "unsaved_changes": "التغييرات غير محفوظة",
            "saved": "تم الحفظ",
            "confirm_remove_config_title": "Are you sure you want to remove your Lovelace UI configuration?",
            "confirm_remove_config_text": "We will automatically generate your Lovelace UI views with your areas and devices if you remove your Lovelace UI configuration.",
            "confirm_unsaved_changes": "You have unsaved changes, are you sure you want to exit?",
            "confirm_unsaved_comments": "Your configuration contains comment(s), these will not be saved. Do you want to continue?",
            "error_parse_yaml": "Unable to parse YAML: {error}",
            "error_invalid_config": "Your configuration is not valid: {error}",
            "error_save_yaml": "Unable to save YAML: {error}",
            "error_remove": "Unable to remove configuration: {error}",
            "resources_moved": "Resources should no longer be added to the Lovelace configuration but can be added in the Lovelace config panel."
          },
          "edit_lovelace": {
            "header": "Title of your Lovelace UI",
            "explanation": "This title is shown above all your views in the Lovelace UI.",
            "edit_title": "Edit title",
            "title": "عنوان"
          },
          "edit_view": {
            "header": "View Configuration",
            "header_name": "{name} عرض التكوين",
            "add": "Add view",
            "edit": "Edit view",
            "delete": "Delete view",
            "move_left": "Move view left",
            "move_right": "Move view right",
            "tab_settings": "Settings",
            "tab_badges": "Badges",
            "tab_visibility": "الرؤية",
            "visibility": {
              "select_users": "تحديد المستخدمين الذين يجب أن يروا طريقة العرض هذه في التنقل"
            }
          },
          "edit_badges": {
            "panel_mode": "These badges will not be displayed because this view is in \"Panel Mode\"."
          },
          "edit_card": {
            "header": "Card Configuration",
            "typed_header": "{type} تكوين البطاقة",
            "pick_card": "Which card would you like to add?",
            "pick_card_view_title": "Which card would you like to add to your {name} view?",
            "toggle_editor": "Toggle Editor",
            "unsaved_changes": "لديك تغييرات غير محفوظة",
            "confirm_cancel": "هل أنت متأكد من الإلغاء؟",
            "show_visual_editor": "Show Visual Editor",
            "show_code_editor": "Show Code Editor",
            "add": "Add Card",
            "edit": "تصحيح",
            "clear": "Clear",
            "delete": "حذف",
            "duplicate": "بطاقة مكررة",
            "move": "نقل",
            "move_before": "Move card before",
            "move_after": "Move card after",
            "options": "المزيد من الخيارات",
            "search_cards": "Search cards"
          },
          "move_card": { "header": "Choose a view to move the card to" },
          "select_view": {
            "header": "Choose a view",
            "dashboard_label": "Dashboard"
          },
          "suggest_card": {
            "header": "We created a suggestion for you",
            "create_own": "Pick different card",
            "add": "Add to Lovelace UI"
          },
          "save_config": {
            "header": "Take control of your Lovelace UI",
            "para": "This dashboard is currently being maintained by Home Assistant. It is automatically updated when new entities or Lovelace UI components become available. If you take control, this dashboard will no longer be automatically updated. You can always create a new dashboard in configuration to play around with.",
            "para_sure": "هل أنت متأكد أنك تريد التحكم في واجهة المستخدم الخاصة بك؟",
            "yaml_mode": "أنت تستخدم وضع YAML للوحة البيانات هذه ، مما يعني أنه لا يمكنك تغيير تكوين Lovelace من واجهة المستخدم. إذا كنت تريد إدارة لوحة التحكم هذه من واجهة المستخدم ، فقم بإزالة \"الوضع: yaml\" من تكوين Lovelace في \"config.yaml.\".",
            "yaml_control": "To take control in YAML mode, create a YAML file with the name you specified in your config for this dashboard, or the default 'ui-lovelace.yaml'.",
            "yaml_config": "To help you start here is the current config of this dashboard:",
            "empty_config": "ابدأ بلوحة معلومات فارغة",
            "cancel": "لا يهم",
            "close": "إغلاق",
            "save": "Take control"
          },
          "migrate": {
            "header": "Configuration Incompatible",
            "para_no_id": "This element doesn't have an ID. Please add an ID to this element in 'ui-lovelace.yaml'.",
            "para_migrate": "Home Assistant can add IDs to all your cards and views automatically for you by pressing the 'Migrate configuration' button.",
            "migrate": "Migrate configuration"
          },
          "action-editor": {
            "navigation_path": "Navigation Path",
            "url_path": "URL Path",
            "editor_service_data": "Service data can only be entered in the code editor",
            "actions": {
              "default_action": "Default Action",
              "call-service": "Call Service",
              "more-info": "More Info",
              "toggle": "Toggle",
              "navigate": "Navigate",
              "url": "URL",
              "none": "No Action"
            }
          },
          "card": {
            "alarm-panel": {
              "name": "Alarm Panel",
              "available_states": "Available States",
              "description": "تسمح لك بطاقة لوحة الإنذار بتفعيل وتعطيل لوحة التحكم الخاصة بالانذار ."
            },
            "calendar": {
              "name": "Calendar",
              "description": "The Calendar card displays a calendar including day, week and list views",
              "inital_view": "Initial View",
              "calendar_entities": "Calendar Entities",
              "views": {
                "dayGridMonth": "Month",
                "dayGridDay": "Day",
                "listWeek": "List"
              }
            },
            "conditional": {
              "name": "Conditional",
              "description": "تعرض البطاقة الشرطية بطاقة أخرى استنادًا إلى حالات الكيان.",
              "conditions": "شروط",
              "card": "بطاقة",
              "state_equal": "الحالة تساوي",
              "state_not_equal": "الحالة لا تساوي",
              "current_state": "الحالي",
              "condition_explanation": "ستظهر البطاقة عند استيفاء جميع الشروط أدناه.",
              "change_type": "نوع التغيير"
            },
            "config": { "required": "Required", "optional": "Optional" },
            "entities": {
              "name": "Entities",
              "show_header_toggle": "Show Header Toggle?",
              "toggle": "Toggle entities.",
              "description": "بطاقة الكيانات هي أكثر أنواع البطاقات شيوعًا. تقوم بتجميع العناصر معًا في قوائم.",
              "special_row": "special row",
              "edit_special_row": "View the details of this row by clicking the edit button",
              "entity_row_editor": "Entity Row Editor",
              "secondary_info_values": {
                "none": "No Secondary Info",
                "entity-id": "Entity ID",
                "last-changed": "Last Changed",
                "last-triggered": "Last Triggered",
                "position": "Position",
                "tilt-position": "Tilt Position",
                "brightness": "Brightness",
                "last-updated": "Last Updated"
              },
              "entity_row": {
                "divider": "Divider",
                "call-service": "Call Service",
                "section": "Section",
                "weblink": "Web Link",
                "attribute": "Attribute",
                "buttons": "Buttons",
                "conditional": "Conditional",
                "cast": "Cast",
                "button": "Button"
              }
            },
            "entity": {
              "name": "الكيان",
              "description": "تمنحك بطاقة الكيان نظرة عامة سريعة عن حالة الكيان."
            },
            "button": {
              "name": "زر",
              "description": "تتيح لك بطاقة الأزرار إضافة أزرار لأداء المهام.",
              "default_action_help": "The default action depends on the entity's capabilities, it will either be toggled or the more info will be shown."
            },
            "entity-filter": {
              "name": "Entity Filter",
              "description": "تتيح لك بطاقة تصفية الكيانات تحديد قائمة بالكيانات التي تريد تتبعها فقط عندما تكون في حالة معينة."
            },
            "gauge": {
              "name": "Gauge",
              "severity": {
                "define": "Define Severity?",
                "green": "Green",
                "red": "Red",
                "yellow": "Yellow"
              },
              "description": "بطاقة القياس هي بطاقة أساسية تسمح برؤية بيانات الاستشعار بصريًا."
            },
            "glance": {
              "name": "Glance",
              "columns": "Columns",
              "description": "بطاقة اللمحة مفيدة لتجميع أجهزة استشعار متعددة في نظرة عامة مدمجة."
            },
            "grid": {
              "name": "Grid",
              "description": "The Grid card allows you to show multiple cards in a grid."
            },
            "logbook": {
              "name": "Logbook",
              "description": "The Logbook card shows a list of events for entities."
            },
            "history-graph": {
              "name": "History Graph",
              "description": "تسمح لك بطاقة الرسم البياني التاريخي بعرض رسم بياني لكل من الكيانات المذكورة."
            },
            "horizontal-stack": {
              "name": "Horizontal Stack",
              "description": "تتيح لك بطاقة التكديس الأفقي تجميع عدة بطاقات معًا ، بحيث تكون دائمًا بجانب بعضها البعض في مساحة عمود واحد."
            },
            "humidifier": {
              "name": "المرطب",
              "description": "تتيح بطاقة المرطب التحكم في كيان المرطب. يسمح لك بتغيير الرطوبة ووضع الكيان."
            },
            "iframe": {
              "name": "Webpage",
              "description": "تسمح لك بطاقة صفحة الويب بتضمين صفحة ويب مباشرةً في Home Assistant."
            },
            "light": {
              "name": "Light",
              "description": "تسمح لك بطاقة الضوء بتغيير سطوع الضوء."
            },
            "generic": {
              "aspect_ratio": "Aspect Ratio",
              "attribute": "السمه",
              "camera_image": "Camera Entity",
              "camera_view": "عرض الكاميرا",
              "double_tap_action": "تأثير النقر المزدوج",
              "entities": "Entities",
              "entity": "Entity",
              "hold_action": "Hold Action",
              "hours_to_show": "Hours to Show",
              "icon": "Icon",
              "icon_height": "Icon Height",
              "image": "Image Path",
              "maximum": "Maximum",
              "manual": "يدويا",
              "manual_description": "هل تريد إضافة بطاقة مخصصة أو ترغب فقط في كتابة yaml يدويًا؟",
              "minimum": "Minimum",
              "name": "Name",
              "refresh_interval": "Refresh Interval",
              "show_icon": "Show Icon?",
              "show_name": "أظهر الاسم؟",
              "show_state": "Show State?",
              "tap_action": "Tap Action",
              "title": "Title",
              "theme": "Theme",
              "no_theme": "لا توجد تصاميم متاحة",
              "unit": "Unit",
              "url": "URL",
              "state": "الحالة",
              "secondary_info_attribute": "سمة المعلومات الثانوية",
              "search": "بحث",
              "state_color": "Color icons based on state?"
            },
            "map": {
              "name": "Map",
              "geo_location_sources": "Geolocation Sources",
              "dark_mode": "Dark Mode?",
              "default_zoom": "Default Zoom",
              "hours_to_show": "ساعات للعرض",
              "source": "Source",
              "description": "بطاقة الخريطة التي تتيح لك عرض الكيانات على الخريطة."
            },
            "markdown": {
              "name": "Markdown",
              "content": "Content",
              "description": "يتم استخدام بطاقة Markdown لعرض Markdown."
            },
            "media-control": {
              "name": "Media Control",
              "description": "يتم استخدام بطاقة التحكم بالوسائط لعرض كيانات مشغل الوسائط على واجهة مع عناصر تحكم سهلة الاستخدام."
            },
            "picture": {
              "name": "Picture",
              "description": "تسمح لك بطاقة الصورة بتعيين صورة لاستخدامها في التنقل إلى مسارات مختلفة في واجهتك أو لاستدعاء خدمة."
            },
            "picture-elements": {
              "name": "Picture Elements",
              "description": "بطاقة عناصر الصورة هي واحدة من أكثر أنواع البطاقات تنوعا. تسمح لك البطاقات بوضع الرموز أو النص وحتى الخدمات! على صورة تستند إلى إحداثيات."
            },
            "picture-entity": {
              "name": "Picture Entity",
              "description": "تعرض بطاقة كيان الصورة كيانًا في شكل صورة. بدلاً من الصور من عنوان URL، يمكنه أيضًا عرض صورة كيانات الكاميرا."
            },
            "picture-glance": {
              "name": "Picture Glance",
              "description": "تعرض بطاقة \"لمحة الصورة\" صورة وحالات كيان مقابلة كرمز. تسمح الكيانات الموجودة على الجانب الأيمن بإجراءات التبديل ، بينما تظهر جهات أخرى حوار المعلومات أكثر."
            },
            "plant-status": {
              "name": "Plant Status",
              "description": "بطاقة حالة النبات هي لجميع محبين النباتات."
            },
            "sensor": {
              "name": "Sensor",
              "show_more_detail": "Show more detail",
              "graph_type": "Graph Type",
              "description": "تمنحك بطاقة المستشعر لمحة عامة سريعة عن حالة المستشعرات الخاصة بك مع رسم بياني اختياري لتصور التغيير بمرور الوقت."
            },
            "shopping-list": {
              "name": "Shopping List",
              "description": "تتيح لك بطاقة قائمة التسوق إضافة عناصر وتحريرها وإلغاء تحديدها ومسحها من قائمة التسوق الخاصة بك.",
              "integration_not_loaded": "This card requires the `shopping_list` integration to be set up."
            },
            "thermostat": {
              "name": "Thermostat",
              "description": "تتيح بطاقة الترموستات التحكم في كيان المناخ لديك. يسمح لك بتغيير درجة حرارة الكيان ووضعه."
            },
            "vertical-stack": {
              "name": "Vertical Stack",
              "description": "تسمح لك بطاقة التكديس الرأسي بتجميع بطاقات متعددة بحيث تكون دائمًا في نفس العمود."
            },
            "weather-forecast": {
              "name": "Weather Forecast",
              "description": "تعرض بطاقة توقعات الطقس حالة الطقس. من المفيد جدًا تضمينه في الواجهات التي يعرضها الأشخاص على الحائط.",
              "show_forecast": "التوقعات"
            }
          },
          "view": {
            "panel_mode": {
              "title": "Panel Mode?",
              "description": "This renders the first card at full width. Other cards in this view as well as badges will not be rendered.",
              "warning_multiple_cards": "تحتوي طريقة العرض هذه على أكثر من بطاقة ، ولكن يمكن أن تعرض طريقة عرض اللوحة بطاقة واحدة فقط."
            }
          },
          "cardpicker": {
            "no_description": "لا يوجد وصف متاح.",
            "custom_card": "معدل",
            "domain": "Domain",
            "entity": "Entity",
            "by_entity": "By Entity",
            "by_card": "By Card"
          },
          "header-footer": {
            "header": "Header",
            "footer": "Footer",
            "choose_header_footer": "Choose a {type}",
            "types": {
              "graph": { "name": "Graph" },
              "picture": { "name": "Picture" },
              "buttons": { "name": "Buttons" }
            }
          },
          "sub-element-editor": {
            "types": {
              "header": "Header Editor",
              "footer": "Footer Editor",
              "row": "Entity Row Editor"
            }
          }
        },
        "warning": {
          "attribute_not_found": "السمة {attribute} غير متاحة في: {entity}",
          "entity_not_found": "الجهاز غير متوفر: {entity}",
          "entity_non_numeric": "Entity is non-numeric: {entity}",
          "entity_unavailable": "العنصر غير متوفر",
          "starting": "Home Assistant يبدأ، قد لا يكون كل شيء متاح حتى الآن"
        },
        "changed_toast": {
          "message": "The Lovelace UI configuration for this dashboard was updated. Refresh to see changes?"
        },
        "reload_lovelace": "إعادة تحميل واجهة المستخدم"
      },
      "shopping_list": { "start_conversation": "Start conversation" },
      "custom": {
        "external_panel": {
          "question_trust": "Do you trust the external panel {name} at {link}?",
          "complete_access": "It will have access to all data in Home Assistant.",
          "hide_message": "Check docs for the panel_custom component to hide this message"
        }
      }
    }
  }
}
