{
  "panel": {
    "calendar": "Kalendar",
    "config": "Konfiguracija",
    "states": "Pregled",
    "map": "Karta",
    "logbook": "Dnevnik",
    "history": "Povijest",
    "mailbox": "Pošta",
    "shopping_list": "Popis za kupovinu",
    "developer_tools": "Razvojni alati",
    "media_browser": "Media Browser",
    "profile": "Profil"
  },
  "state": {
    "default": {
      "on": "On",
      "off": "Off",
      "unknown": "Nepoznato",
      "unavailable": "Nedostupan"
    },
    "alarm_control_panel": {
      "armed": "Aktiviran",
      "armed_away": "Aktiviran odsutno",
      "armed_custom_bypass": "Aktiviran",
      "armed_home": "Aktiviran doma",
      "armed_night": "Aktiviran nočni",
      "arming": "Aktiviranje",
      "disarmed": "Deaktiviran",
      "disarming": "Deaktiviranje",
      "pending": "U tijeku",
      "triggered": "Okinut"
    },
    "automation": { "off": "Isključen", "on": "Uključen" },
    "binary_sensor": {
      "battery": { "off": "Normalno", "on": "Prazna" },
      "cold": { "off": "Normalno", "on": "Hladno" },
      "connectivity": { "off": "Nije spojen", "on": "Spojen" },
      "default": { "off": "Isključen", "on": "Uključen" },
      "door": { "off": "Zatvoreno", "on": "Otvori" },
      "garage_door": { "off": "Zatvoren", "on": "Otvoreno" },
      "gas": { "off": "Čisto", "on": "Otkriveno" },
      "heat": { "off": "Normalno", "on": "Vruće" },
      "lock": { "off": "Zaključano", "on": "Otključano" },
      "moisture": { "off": "Suho", "on": "Mokro" },
      "motion": { "off": "Čisto", "on": "Otkriveno" },
      "occupancy": { "off": "Čisto", "on": "Otkriveno" },
      "opening": { "off": "Zatvoreno", "on": "Otvoreno" },
      "presence": { "off": "Odsutan", "on": "Doma" },
      "problem": { "off": "OK", "on": "Problem" },
      "safety": { "off": "Sigurno", "on": "Nesigurno" },
      "smoke": { "off": "Čisto", "on": "Otkriveno" },
      "sound": { "off": "Čisto", "on": "Otkriveno" },
      "vibration": { "off": "Čisto", "on": "Otkriveno" },
      "window": { "off": "Zatvoreno", "on": "Otvoreno" }
    },
    "calendar": { "off": "Isključen", "on": "Uključen" },
    "camera": {
      "idle": "Neaktivan",
      "recording": "Snimanje",
      "streaming": "Odašilja"
    },
    "climate": {
      "cool": "Hlađenje",
      "dry": "Suho",
      "fan_only": "Samo ventilator",
      "heat": "Grijanje",
      "heat_cool": "Grijanje/Hlađenje",
      "off": "Isključen"
    },
    "configurator": {
      "configure": "Konfiguriranje",
      "configured": "Konfiguriran"
    },
    "cover": {
      "closed": "Zatvoreno",
      "closing": "Zatvaranje",
      "open": "Otvoreno",
      "opening": "Otvaranje",
      "stopped": "zaustavljen"
    },
    "device_tracker": { "not_home": "Odsutan" },
    "fan": { "off": "Isključen", "on": "Uključen" },
    "group": {
      "closed": "Zatvoreno",
      "closing": "Zatvaranje",
      "home": "Doma",
      "locked": "Zaključano",
      "not_home": "Odsutan",
      "off": "Isključen",
      "ok": "U redu",
      "on": "Uključen",
      "open": "Otvoreno",
      "opening": "Otvaranje",
      "problem": "Problem",
      "stopped": "Zautavljeno",
      "unlocked": "Otključano"
    },
    "input_boolean": { "off": "Isključen", "on": "Uključen" },
    "light": { "off": "Isključen", "on": "Uključen" },
    "lock": { "locked": "Zaključan", "unlocked": "Otključan" },
    "media_player": {
      "idle": "Neaktivan",
      "off": "Isključen",
      "on": "Uključen",
      "paused": "Pauzirano",
      "playing": "Prikazivanje",
      "standby": "U stanju čekanja"
    },
    "person": { "home": "Doma" },
    "plant": { "ok": "u redu", "problem": "Problem" },
    "remote": { "off": "Isključen", "on": "Uključen" },
    "scene": { "scening": "Scene" },
    "script": { "off": "Isključen", "on": "Uključen" },
    "sensor": { "off": "Isključen", "on": "Uključen" },
    "sun": {
      "above_horizon": "Iznad horizonta",
      "below_horizon": "Ispod horizonta"
    },
    "switch": { "off": "Isključen", "on": "Uključen" },
    "timer": {
      "active": "aktivan",
      "idle": "neaktivan",
      "paused": "pauzirano"
    },
    "vacuum": {
      "cleaning": "Čišćenje",
      "docked": "Usidreni",
      "error": "Greška",
      "idle": "Neaktivan",
      "off": "Ugašeno",
      "on": "Upaljeno",
      "paused": "Pauzirano",
      "returning": "Povratak na dok"
    },
    "weather": {
      "clear-night": "Vedro, noć",
      "cloudy": "Oblačno",
      "exceptional": "Izuzetan",
      "fog": "Magla",
      "hail": "Tuča",
      "lightning": "Munja",
      "lightning-rainy": "Munja, kišna",
      "partlycloudy": "Djelomično oblačno",
      "pouring": "Lije",
      "rainy": "Kišovito",
      "snowy": "Snježno",
      "snowy-rainy": "Snježno, kišno",
      "sunny": "Sunčano",
      "windy": "Vjetrovito",
      "windy-variant": "Vjetrovito"
    },
    "zwave": {
      "default": {
        "dead": "Mrtav",
        "initializing": "Inicijalizacija",
        "ready": "Spreman",
        "sleeping": "Spavanje"
      },
      "query_stage": {
        "dead": "Mrtav ({query_stage})",
        "initializing": "Inicijalizacija ( {query_stage} )"
      }
    }
  },
  "state_attributes": {
    "climate": {
      "fan_mode": { "off": "Isključen", "on": "Uključen", "auto": "Auto" },
      "preset_mode": {
        "none": "Ništa",
        "eco": "Eko",
        "away": "Odsutan",
        "boost": "Pojačano",
        "comfort": "Udobno",
        "home": "Doma",
        "sleep": "Spavanje",
        "activity": "Aktivnost"
      },
      "hvac_action": {
        "off": "Isključen",
        "heating": "Grijanje",
        "cooling": "Hlađenje",
        "drying": "Sušenje",
        "idle": "Neaktivan",
        "fan": "Ventilator"
      }
    },
    "humidifier": {
      "mode": {
        "normal": "Normal",
        "eco": "Eco",
        "away": "Away",
        "boost": "Boost",
        "comfort": "Comfort",
        "home": "Home",
        "sleep": "Sleep",
        "auto": "Auto",
        "baby": "Baby"
      }
    }
  },
  "state_badge": {
    "default": {
      "unknown": "Nepoznato",
      "unavailable": "Nedostupno",
      "error": "Greška",
      "entity_not_found": "Entitet nije pronađen"
    },
    "alarm_control_panel": {
      "armed": "Aktivirano",
      "disarmed": "Deaktiviraj",
      "armed_home": "Aktivirano",
      "armed_away": "Aktivirano",
      "armed_night": "Aktivirano",
      "armed_custom_bypass": "Aktivirano",
      "pending": "U tijeku",
      "arming": "Aktiviranje",
      "disarming": "Deaktiviraj",
      "triggered": "Okinut"
    },
    "device_tracker": { "home": "Doma", "not_home": "Odsutan" },
    "person": { "home": "Doma", "not_home": "Odsutan" }
  },
  "groups": {
    "system-admin": "Administratori",
    "system-users": "Korisnici",
    "system-read-only": "Korisnici sa pravima samo za čitanje"
  },
  "config_entry": {
    "disabled_by": {
      "user": "Korisnik",
      "integration": "Integracija",
      "config_entry": "Stavka konfiguracije"
    }
  },
  "ui": {
    "auth_store": {
      "ask": "Želite li spremiti ovu prijavu?",
      "decline": "Ne hvala",
      "confirm": "Spremi prijavu"
    },
    "card": {
      "alarm_control_panel": {
        "code": "Kod",
        "clear_code": "Vedro",
        "disarm": "Deaktiviraj",
        "arm_home": "Aktiviran doma",
        "arm_away": "Aktiviran odsutno",
        "arm_night": "Aktiviran nočni",
        "arm_custom_bypass": "Prilagođena premosnica"
      },
      "automation": {
        "last_triggered": "Zadnje aktivirano",
        "trigger": "Okidač"
      },
      "camera": { "not_available": "Slika nije dostupna" },
      "climate": {
        "currently": "Trenutno",
        "on_off": "Uključivanje / isključivanje",
        "target_temperature": "Ciljana temperatura",
        "target_temperature_entity": "{name} target temperature",
        "target_temperature_mode": "{name} target temperature {mode}",
        "current_temperature": "{name} current temperature",
        "heating": "{name} heating",
        "cooling": "{name} cooling",
        "high": "high",
        "low": "low",
        "target_humidity": "Ciljana vlažnost",
        "operation": "operacija",
        "fan_mode": "Način rada s ventilatorom",
        "swing_mode": "Swing način rada",
        "preset_mode": "Zadano",
        "away_mode": "Način rada: Odsutan",
        "aux_heat": "Pomoćno grijanje"
      },
      "counter": {
        "actions": {
          "increment": "increment",
          "decrement": "decrement",
          "reset": "reset"
        }
      },
      "cover": { "position": "Pozicija", "tilt_position": "Položaj nagiba" },
      "fan": {
        "speed": "Brzina",
        "oscillate": "Oscilirati",
        "direction": "Smjer",
        "forward": "Naprijed",
        "reverse": "Nazad"
      },
      "humidifier": {
        "humidity": "Target humidity",
        "mode": "Mode",
        "target_humidity_entity": "{name} target humidity",
        "on_entity": "{name} on"
      },
      "light": {
        "brightness": "Svjetlina",
        "color_temperature": "Temperatura boje",
        "white_value": "Bijela vrijednost",
        "effect": "Efekt"
      },
      "lock": { "code": "Kod", "lock": "zaključati", "unlock": "Otključati" },
      "media_player": {
        "source": "Izvor",
        "sound_mode": "Način zvuka",
        "browse_media": "Browse media",
        "turn_on": "Turn on",
        "turn_off": "Turn off",
        "media_play": "Play",
        "media_play_pause": "Play/pause",
        "media_next_track": "Next",
        "media_previous_track": "Previous",
        "text_to_speak": "Tekst u govor"
      },
      "persistent_notification": { "dismiss": "Odbaci" },
      "scene": { "activate": "Aktivirati" },
      "script": {
        "execute": "Izvršiti",
        "cancel": "Cancel",
        "cancel_multiple": "Cancel {number}"
      },
      "service": { "run": "Pokreni" },
      "timer": {
        "actions": {
          "start": "početak",
          "pause": "pauza",
          "cancel": "otkaži",
          "finish": "Završiti"
        }
      },
      "vacuum": {
        "actions": {
          "resume_cleaning": "Nastavi čišćenje",
          "return_to_base": "Povratak na dok",
          "start_cleaning": "Započnite čišćenje",
          "turn_on": "Uključiti",
          "turn_off": "Isključiti"
        }
      },
      "water_heater": {
        "currently": "Trenutno",
        "on_off": "Uključeno/Isključeno",
        "target_temperature": "Ciljana temperatura",
        "operation": "Operacija",
        "away_mode": "Način rada: Odsutan"
      },
      "weather": {
        "attributes": {
          "air_pressure": "Tlak zraka",
          "humidity": "Vlažnost",
          "temperature": "Temperatura",
          "visibility": "Vidljivost",
          "wind_speed": "Brzina vjetra",
          "precipitation": "Precipitation"
        },
        "cardinal_direction": {
          "e": "I",
          "ene": "ISI",
          "ese": "ESE",
          "n": "N",
          "ne": "NE",
          "nne": "NNE",
          "nw": "NW",
          "nnw": "SSZ",
          "s": "J",
          "se": "JI",
          "sse": "JJI",
          "ssw": "JJZ",
          "sw": "JZ",
          "w": "Z",
          "wnw": "ZSZ",
          "wsw": "ZJZ"
        },
        "day": "Day",
        "night": "Night",
        "forecast": "Prognoza",
        "high": "High",
        "low": "Low"
      }
    },
    "common": {
      "and": "and",
      "continue": "Continue",
      "previous": "Previous",
      "loading": "Učitavam",
      "refresh": "Refresh",
      "cancel": "Otkazati",
      "delete": "Delete",
      "remove": "Remove",
      "enable": "Enable",
      "disable": "Disable",
      "close": "Close",
      "leave": "Leave",
      "stay": "Stay",
      "next": "Next",
      "back": "Back",
      "undo": "Undo",
      "save": "Spremi",
      "rename": "Rename",
      "yes": "Da",
      "no": "Ne",
      "not_now": "Not now",
      "skip": "Skip",
      "menu": "Menu",
      "overflow_menu": "Overflow menu",
      "successfully_saved": "Uspješno spremljeno",
      "successfully_deleted": "Successfully deleted",
      "error_required": "Required",
      "copied": "Copied"
    },
    "components": {
      "logbook": {
        "entries_not_found": "No logbook entries found.",
        "by": "by",
        "by_service": "by service",
        "messages": {
          "was_away": "was away",
          "was_at_state": "was at {state}",
          "rose": "rose",
          "set": "set",
          "was_low": "was low",
          "was_normal": "was normal",
          "was_connected": "was connected",
          "was_disconnected": "was disconnected",
          "was_opened": "was opened",
          "was_closed": "was closed",
          "was_unlocked": "was unlocked",
          "was_locked": "was locked",
          "was_plugged_in": "was plugged in",
          "was_unplugged": "was unplugged",
          "was_at_home": "was at home",
          "was_unsafe": "was unsafe",
          "was_safe": "was safe",
          "detected_device_class": "detected {device_class}",
          "cleared_device_class": "cleared (no {device_class} detected)",
          "turned_off": "turned off",
          "turned_on": "turned on",
          "changed_to_state": "changed to {state}",
          "became_unavailable": "became unavailable"
        }
      },
      "entity": {
        "entity-picker": {
          "entity": "Entitet",
          "clear": "Clear",
          "show_entities": "Prikaži entitete"
        },
        "entity-attribute-picker": {
          "attribute": "Attribute",
          "show_attributes": "Show attributes"
        }
      },
      "user-picker": {
        "no_user": "No user",
        "add_user": "Add user",
        "remove_user": "Remove user"
      },
      "device-picker": {
        "clear": "Obriši",
        "toggle": "Preklopi",
        "show_devices": "Prikaži uređaje",
        "device": "Uređaj",
        "no_area": "No area"
      },
      "area-picker": {
        "clear": "Obriši",
        "show_areas": "Pokažite područja",
        "area": "Područje",
        "add_new": "Dodajte novo područje…",
        "add_dialog": {
          "title": "Dodajte novo područje",
          "text": "Unesite naziv novog područja.",
          "name": "Naziv",
          "add": "Dodaj",
          "failed_create_area": "Nije uspjelo stvaranje područja."
        }
      },
      "picture-upload": {
        "label": "Picture",
        "unsupported_format": "Unsupported format, please choose a JPEG, PNG or GIF image."
      },
      "date-range-picker": {
        "start_date": "Start date",
        "end_date": "End date",
        "select": "Select"
      },
      "relative_time": {
        "never": "Nikada",
        "just_now": "Just now",
        "duration": {
          "second": "{count} {count, plural,\n  one {sekunda}\n  other {sekunde}\n}",
          "minute": "{count} {count, plural,\n  one {minuta}\n  other {minuta}\n}",
          "hour": "{count} {count, plural,\n  one {sat}\n  other {sati}\n}",
          "day": "{count} {count, plural,\n  one {dan}\n  other {dana}\n}",
          "week": "{count} {count, plural,\n  one {week}\n  other {weeks}\n}"
        },
        "past_duration": {
          "second": "{count} {count, plural,\n  one {second}\n  other {seconds}\n} ago",
          "minute": "{count} {count, plural,\n  one {minute}\n  other {minutes}\n} ago",
          "hour": "{count} {count, plural,\n  one {hour}\n  other {hours}\n} ago",
          "day": "{count} {count, plural,\n  one {day}\n  other {days}\n} ago",
          "week": "{count} {count, plural,\n  one {week}\n  other {weeks}\n} ago"
        },
        "future_duration": {
          "second": "In {count} {count, plural,\n  one {second}\n  other {seconds}\n}",
          "minute": "In {count} {count, plural,\n  one {minute}\n  other {minutes}\n}",
          "hour": "In {count} {count, plural,\n  one {hour}\n  other {hours}\n}",
          "day": "In {count} {count, plural,\n  one {day}\n  other {days}\n}",
          "week": "In {count} {count, plural,\n  one {week}\n  other {weeks}\n}"
        },
        "future": "Za {time}",
        "past": "{time} prije"
      },
      "history_charts": {
        "loading_history": "Učitavanje povijesti stanja ...",
        "no_history_found": "Nije pronađena povijest stanja."
      },
      "service-picker": { "service": "Usluga" },
      "related-items": {
        "no_related_found": "No related items found.",
        "integration": "Integration",
        "device": "Device",
        "area": "Area",
        "entity": "Related entities",
        "group": "Part of the following groups",
        "scene": "Part of the following scenes",
        "script": "Part of the following scripts",
        "automation": "Part of the following automations"
      },
      "data-table": { "search": "Search", "no-data": "No data" },
      "media-browser": {
        "pick": "Pick",
        "play": "Play",
        "play-media": "Play Media",
        "pick-media": "Pick Media",
        "no_items": "No items",
        "choose_player": "Choose Player",
        "media-player-browser": "Media Player Browser",
        "web-browser": "Web Browser",
        "media_player": "Media Player",
        "audio_not_supported": "Your browser does not support the audio element.",
        "video_not_supported": "Your browser does not support the video element.",
        "media_not_supported": "The Browser Media Player does not support this type of media",
        "media_browsing_error": "Media Browsing Error",
        "learn_adding_local_media": "Learn more about adding media in the {documentation}.",
        "local_media_files": "Place your video, audio and image files in the media directory to be able to browse and play them in the browser or on supported media players.",
        "documentation": "documentation",
        "no_local_media_found": "No local media found",
        "no_media_folder": "It looks like you have not yet created a media directory.",
        "setup_local_help": "Check the {documentation} on how to setup local media.",
        "class": {
          "album": "Album",
          "app": "App",
          "artist": "Artist",
          "channel": "Channel",
          "composer": "Composer",
          "contributing_artist": "Contributing Artist",
          "directory": "Library",
          "episode": "Episode",
          "game": "Game",
          "genre": "Genre",
          "image": "Image",
          "movie": "Movie",
          "music": "Music",
          "playlist": "Playlist",
          "podcast": "Podcast",
          "season": "Season",
          "track": "Track",
          "tv_show": "TV Show",
          "url": "URL",
          "video": "Video"
        }
      }
    },
    "dialogs": {
      "quick-bar": {
        "commands": {
          "reload": {
            "reload": "Reload {domain}",
            "core": "Reload location & customizations",
            "group": "Reload groups, group entities, and notify services",
            "automation": "Reload automations",
            "script": "Reload scripts",
            "scene": "Reload scenes",
            "person": "Reload people",
            "zone": "Reload zones",
            "input_boolean": "Reload input booleans",
            "input_text": "Reload input texts",
            "input_number": "Reload input numbers",
            "input_datetime": "Reload input date times",
            "input_select": "Reload input selects",
            "template": "Reload template entities",
            "universal": "Reload universal media player entities",
            "rest": "Reload rest entities and notify services",
            "command_line": "Reload command line entities",
            "filter": "Reload filter entities",
            "statistics": "Reload statistics entities",
            "generic": "Reload generic IP camera entities",
            "generic_thermostat": "Reload generic thermostat entities",
            "homekit": "Reload HomeKit",
            "min_max": "Reload min/max entities",
            "history_stats": "Reload history stats entities",
            "trend": "Reload trend entities",
            "ping": "Reload ping binary sensor entities",
            "filesize": "Reload file size entities",
            "telegram": "Reload telegram notify services",
            "smtp": "Reload SMTP notify services",
            "mqtt": "Reload manually configured MQTT entities",
            "rpi_gpio": "Reload Raspberry Pi GPIO entities"
          },
          "server_control": {
            "perform_action": "{action} Server",
            "restart": "Restart",
            "stop": "Stop"
          },
          "navigation": {
            "navigate_to": "Navigate to {panel}",
            "navigate_to_config": "Navigate to {panel} configuration",
            "logs": "Logs",
            "automation": "Automations",
            "script": "Scripts",
            "integrations": "Integrations",
            "areas": "Areas",
            "scene": "Scenes",
            "helpers": "Helpers",
            "tags": "Tags",
            "person": "People",
            "devices": "Devices",
            "entities": "Entities",
            "lovelace": "Lovelace Dashboards",
            "core": "General",
            "zone": "Zones",
            "users": "Users",
            "info": "Info",
            "customize": "Customizations",
            "server_control": "Server Controls"
          }
        },
        "filter_placeholder": "Entity Filter"
      },
      "voice_command": {
        "did_not_hear": "Home Assistant nije ništa čuo",
        "found": "Pronašao sam za vas sljedeće:",
        "error": "Ups, došlo je do pogreške",
        "how_can_i_help": "Kako mogu pomoći?",
        "label": "Unesite pitanje i pritisnite \"Enter\"",
        "label_voice": "Type and press 'Enter' or tap the microphone to speak"
      },
      "generic": {
        "cancel": "Otkaži",
        "ok": "U redu",
        "default_confirmation_title": "Jeste li sigurni?",
        "close": "close"
      },
      "image_cropper": { "crop": "Crop" },
      "more_info_control": {
        "dismiss": "Dismiss dialog",
        "settings": "Entity settings",
        "edit": "Uredi entitet",
        "details": "Details",
        "history": "History",
        "last_changed": "Last changed",
        "last_updated": "Last updated",
        "script": {
          "last_action": "Posljednja akcija",
          "last_triggered": "Last Triggered"
        },
        "sun": {
          "elevation": "Elevacija",
          "rising": "Izlazi",
          "setting": "Zalazi"
        },
        "updater": { "title": "Upute za ažuriranje" },
        "restored": {
          "not_provided": "This entity is currently unavailable and is an orphan to a removed, changed or dysfunctional integration or device.",
          "remove_intro": "If the entity is no longer in use, you can clean it up by removing it.",
          "remove_action": "Remove entity",
          "confirm_remove_title": "Remove entity?",
          "confirm_remove_text": "Are you sure you want to remove this entity?"
        },
        "vacuum": {
          "status": "Status",
          "commands": "Vacuum cleaner commands:",
          "fan_speed": "Fan speed",
          "start": "Start",
          "pause": "Pause",
          "stop": "Stop",
          "clean_spot": "Clean spot",
          "locate": "Locate",
          "return_home": "Return home",
          "start_pause": "Start/Pause"
        },
        "person": { "create_zone": "Create zone from current location" },
        "cover": {
          "open_tilt_cover": "Open cover tilt",
          "close_tile_cover": "Close cover tilt",
          "stop_cover": "Stop cover from moving"
        }
      },
      "entity_registry": {
        "settings": "Postavke",
        "control": "Kontrola",
        "related": "Vezani",
        "dismiss": "Odbaci",
        "no_unique_id": "This entity does not have a unique ID, therefore its settings cannot be managed from the UI. See the {faq_link} for more detail.",
        "faq": "documentation",
        "editor": {
          "name": "Premosti naziv",
          "icon": "Icon",
          "icon_error": "Icons should be in the format 'prefix:iconname', e.g. 'mdi:home'",
          "entity_id": "ID entiteta",
          "unavailable": "Ovaj entitet trenutno nije dostupan.",
          "enabled_label": "Aktiviraj entitet",
          "enabled_cause": "Deaktivirano zbog {cause}.",
          "enabled_description": "Onemogućeni entiteti neće biti dodani u Home Assistant.",
          "enabled_delay_confirm": "The enabled entities will be added to Home Assistant in {delay} seconds",
          "enabled_restart_confirm": "Restart Home Assistant to finish enabling the entities",
          "delete": "OBRIŠI",
          "confirm_delete": "Jeste li sigurni da želite izbrisati ovaj unos?",
          "update": "AŽURIRAJ",
          "note": "Napomena: to možda neće raditi još sa svim integracijama."
        }
      },
      "helper_settings": {
        "platform_not_loaded": "The {platform} integration is not loaded. Please add it to your configuration either by adding 'default_config:' or ''{platform}:''.",
        "yaml_not_editable": "The settings of this entity cannot be edited from the UI. Only entities set up from the UI are configurable from the UI.",
        "required_error_msg": "This field is required",
        "generic": { "name": "Name", "icon": "Icon" },
        "input_datetime": {
          "date": "Date",
          "time": "Time",
          "datetime": "Date and time",
          "mode": "What do you want to input"
        },
        "input_text": {
          "min": "Minimum length",
          "max": "Maximum length",
          "mode": "Display mode",
          "text": "Text",
          "password": "Password",
          "pattern": "Regex pattern for client-side validation"
        },
        "input_number": {
          "min": "Minimum value",
          "max": "Maximum value",
          "mode": "Display mode",
          "box": "Input field",
          "slider": "Slider",
          "step": "Step size",
          "unit_of_measurement": "Unit of measurement"
        },
        "input_select": {
          "options": "Options",
          "add_option": "Add option",
          "no_options": "There are no options yet.",
          "add": "Add"
        },
        "counter": {
          "minimum": "Minimum value",
          "maximum": "Maximum value",
          "initial": "Initial value",
          "restore": "Restore the last known value when Home Assistant starts",
          "step": "Step size"
        },
        "timer": { "duration": "Duration" }
      },
      "options_flow": {
        "form": { "header": "Opcije" },
        "success": { "description": "Opcije su uspješno spremljene." }
      },
      "config_entry_system_options": {
        "title": "Mogućnosti sustava",
        "enable_new_entities_label": "Aktiviraj novododane entitete.",
        "enable_new_entities_description": "Ako nije aktivno, novootkriveni entiteti neće biti automatski dodani u Home Assistant.",
        "update": "Update"
      },
      "zha_device_info": {
        "manuf": "od {manufacturer}",
        "no_area": "Nema područja",
        "device_signature": "Zigbee device signature",
        "buttons": {
          "add": "Dodaj uređaje",
          "remove": "Ukloni uređaj",
          "clusters": "Manage Clusters",
          "reconfigure": "Ponovno konfiguriraj uređaj",
          "zigbee_information": "Zigbee device signature"
        },
        "services": {
          "reconfigure": "Ponovno konfiguriaj ZHA uređaj (liječenje uređaja). Upotrijebite ovo ako imate problema s uređajem. Ako je uređaj u pitanju uređaj za bateriju, provjerite je li budan i prihvaća naredbe kada koristite ovu uslugu.",
          "updateDeviceName": "Postavite prilagođeni naziv za ovaj uređaj u registru uređaja.",
          "remove": "Uklonite uređaj iz Zigbee mreže.",
          "zigbee_information": "View the Zigbee information for the device."
        },
        "confirmations": {
          "remove": "Jeste li sigurni da želite ukloniti uređaj?"
        },
        "quirk": "Quirk",
        "last_seen": "Zadnje viđeno",
        "power_source": "Izvor napajanja",
        "unknown": "Nepoznato",
        "zha_device_card": {
          "device_name_placeholder": "Korisničko ime",
          "area_picker_label": "Područje",
          "update_name_button": "Ažuriraj naziv"
        }
      },
      "domain_toggler": {
        "title": "Toggle Domains",
        "reset_entities": "Reset Entities"
      },
      "mqtt_device_debug_info": {
        "title": "{device} debug info",
        "deserialize": "Attempt to parse MQTT messages as JSON",
        "entities": "Entities",
        "no_entities": "No entities",
        "no_triggers": "No triggers",
        "payload_display": "Payload display",
        "recent_messages": "{n} most recently received message(s)",
        "show_as_yaml": "Show as YAML",
        "triggers": "Triggers"
      }
    },
    "duration": {
      "second": "{count} {count, plural,\n  one {sekunde}\n  other {sekunde}\n}",
      "minute": "{count} {count, plural,\n  one {minuta}\n  other {minute}\n }",
      "hour": "{count} {count, plural,\n  one {sat}\n  other {sati}\n }",
      "day": "{count} {count, plural,\n  one {dan}\n  other {dani}\n}",
      "week": "{count} {count, plural,\n  one {tjedan}\n  other {tjedni}\n}"
    },
    "login-form": {
      "password": "Lozinka",
      "remember": "Zapamti",
      "log_in": "Prijava"
    },
    "notification_drawer": {
      "click_to_configure": "Kliknite gumb za konfiguriranje {entity}",
      "empty": "Nema obavijesti",
      "title": "Obavijesti",
      "close": "Close",
      "dismiss_all": "Dismiss all"
    },
    "notification_toast": {
      "service_call_failed": "Pokretanje usluge {service} nijeje uspjelo.",
      "connection_lost": "Veza izgubljena. Spajanje...",
      "started": "Home Assistant has started!",
      "starting": "Home Assistant is starting, not everything will be available until it is finished.",
      "triggered": "{name} aktiviran",
      "dismiss": "Dismiss"
    },
    "sidebar": {
      "external_app_configuration": "Konfiguracija aplikacije",
      "sidebar_toggle": "Prekidač bočne trake",
      "done": "Done"
    },
    "panel": {
      "calendar": { "my_calendars": "My Calendars", "today": "Today" },
      "lovelace": {
        "cards": {
          "confirm_delete": "Are you sure you want to delete this card?",
          "empty_state": {
            "title": "Dobrodošli kući",
            "no_devices": "Ova stranica omogućuje upravljanje uređajima, ali izgleda da još niste postavili nikakve uređaje. Idite na stranicu integracije da biste započeli.",
            "go_to_integrations_page": "Idite na stranicu integracija."
          },
          "entities": { "never_triggered": "Nikada pokrenuto" },
          "shopping-list": {
            "checked_items": "Označene stavke",
            "clear_items": "Izbrišite označene stavke",
            "add_item": "Dodaj stavku"
          },
          "picture-elements": {
            "hold": "Držite:",
            "tap": "Dodirnite:",
            "navigate_to": "Idite do {location}",
            "url": "Otvori prozor za {url_path}",
            "toggle": "Preklopi {name}",
            "call_service": "Pozovi servis {name}",
            "more_info": "Prikaži više informacija: {name}"
          },
          "safe-mode": {
            "header": "Safe Mode Activated",
            "description": "Home Assistant ran into trouble while loading your configuration and is now running in safe mode. Take a look at the error log to see what went wrong."
          },
          "starting": {
            "description": "Home Assistant is starting, please wait..."
          }
        },
        "unused_entities": {
          "title": "Neiskorišteni entiteti",
          "available_entities": "To su entiteti koji su vam dostupni, ali još nisu u vašem korisničkom sučelju Lovelace.",
          "select_to_add": "Odaberite entitete koje želite dodati na karticu, a zatim kliknite gumb \"Dodaj karticu\".",
          "entity": "Entitet",
          "entity_id": "ID entiteta",
          "domain": "Domena",
          "last_changed": "Zadnje promijenjeno",
          "search": "Search entities",
          "no_data": "No unused entities found"
        },
        "add_entities": {
          "yaml_unsupported": "You cannot use this function when using Lovelace UI in YAML mode.",
          "generated_unsupported": "You can only use this function when you have taken control of the Lovelace UI.",
          "saving_failed": "Saving Lovelace UI configuration failed."
        },
        "views": {
          "confirm_delete": "Delete view?",
          "confirm_delete_text": "Are you sure you want to delete your ''{name}'' view?",
          "confirm_delete_existing_cards": "Deleting this view will also remove the cards",
          "confirm_delete_existing_cards_text": "Are you sure you want to delete your ''{name}'' view? The view contains {number} cards that will be deleted. This action cannot be undone."
        },
        "menu": {
          "configure_ui": "Konfiguriraj UI",
          "help": "Pomoć",
          "start_conversation": "Start conversation",
          "reload_resources": "Reload resources",
          "exit_edit_mode": "Exit UI edit mode",
          "close": "Zatvoriti",
          "refresh": "Osvježi"
        },
        "reload_resources": {
          "refresh_header": "Do you want to refresh?",
          "refresh_body": "You have to refresh the page to complete the reload. Do you want to refresh now?"
        },
        "editor": {
          "header": "Uredi UI",
          "menu": {
            "open": "Otvori Lovelace izbornik",
            "raw_editor": "Tekstualni urednik"
          },
          "common": {
            "edit": "Edit",
            "clear": "Clear",
            "add": "Add",
            "none": "None"
          },
          "raw_editor": {
            "header": "Uredi konfiguraciju",
            "save": "Spremi",
            "unsaved_changes": "Nespremljene promjene",
            "saved": "Spremljeno",
            "confirm_remove_config_title": "Are you sure you want to remove your Lovelace UI configuration?",
            "confirm_remove_config_text": "We will automatically generate your Lovelace UI views with your areas and devices if you remove your Lovelace UI configuration.",
            "confirm_unsaved_changes": "Imate nespremljene izmjene. Jeste li sigurni da želite napustiti?",
            "confirm_unsaved_comments": "Vaša konfiguracija sadrži komentare, oni neće biti spremljeni. Želite li nastaviti?",
            "error_parse_yaml": "Nije moguće analizirati YAML: {error}",
            "error_invalid_config": "Vaša konfiguracija nije valjana: {error}",
            "error_save_yaml": "Nije moguće spremiti YAML: {error}",
            "error_remove": "Unable to remove configuration: {error}",
            "resources_moved": "Resources should no longer be added to the Lovelace configuration but can be added in the Lovelace config panel."
          },
          "edit_lovelace": {
            "header": "Naslov vašeg Lovelace UI",
            "explanation": "Ovaj naslov prikazan je iznad svih vaših prikaza u Lovelace.",
            "edit_title": "Uredi naslov",
            "title": "Title"
          },
          "edit_view": {
            "header": "Pogledaj konfiguraciju",
            "header_name": "{name} View Configuration",
            "add": "Dodaj prikaz",
            "edit": "Uredi prikaz",
            "delete": "Izbriši prikaz",
            "move_left": "Move view left",
            "move_right": "Move view right",
            "tab_settings": "Settings",
            "tab_badges": "Badges",
            "tab_visibility": "Visibility",
            "visibility": {
              "select_users": "Select which users should see this view in the navigation"
            }
          },
          "edit_badges": {
            "panel_mode": "These badges will not be displayed because this view is in \"Panel Mode\"."
          },
          "edit_card": {
            "header": "Konfiguracija Kartice",
            "typed_header": "{type} Card Configuration",
            "pick_card": "Odaberite karticu koju želite dodati.",
            "pick_card_view_title": "Which card would you like to add to your {name} view?",
            "toggle_editor": "Uključi uređivač",
            "unsaved_changes": "You have unsaved changes",
            "confirm_cancel": "Are you sure you want to cancel?",
            "show_visual_editor": "Show Visual Editor",
            "show_code_editor": "Show Code Editor",
            "add": "Dodaj karticu",
            "edit": "Uredi",
            "clear": "Clear",
            "delete": "Izbrisati",
            "duplicate": "Duplicate card",
            "move": "Premjesti",
            "move_before": "Move card before",
            "move_after": "Move card after",
            "options": "Više mogućnosti",
            "search_cards": "Search cards"
          },
          "move_card": { "header": "Choose a view to move the card to" },
          "select_view": {
            "header": "Choose a view",
            "dashboard_label": "Dashboard"
          },
          "suggest_card": {
            "header": "We created a suggestion for you",
            "create_own": "Pick different card",
            "add": "Add to Lovelace UI"
          },
          "save_config": {
            "header": "Preuzmite kontrolu nad Lovelace UI",
            "para": "Home Assistant će prema zadanim postavkama održavati vaše korisničko sučelje, ažurirati ga kada novi entiteti ili Lovelace komponente postanu dostupni. Ako preuzmete kontrolu, više nećemo automatski vršiti izmjene za vas.",
            "para_sure": "Jeste li sigurni da želite preuzeti kontrolu nad svojim korisničkim sučeljem?",
            "yaml_mode": "You are using YAML mode for this dashboard, which means you cannot change your Lovelace config from the UI. If you want to manage this dashboard from the UI, remove 'mode: yaml' from your Lovelace configuration in 'configuration.yaml.'.",
            "yaml_control": "To take control in YAML mode, create a YAML file with the name you specified in your config for this dashboard, or the default 'ui-lovelace.yaml'.",
            "yaml_config": "To help you start here is the current config of this dashboard:",
            "empty_config": "Start with an empty dashboard",
            "cancel": "Nema veze",
            "close": "Close",
            "save": "Preuzmi kontrolu"
          },
          "migrate": {
            "header": "Konfiguracija nije kompatibilna",
            "para_no_id": "Ovaj element nema ID. Dodajte ID ovom elementu u 'ui-lovelace.yaml'.",
            "para_migrate": "Home Assistant može dodati ID-ove na sve vaše kartice i pogleda automatski za vas pritiskom na gumb 'Migriraj konfiguriranje'.",
            "migrate": "Migriraj konfiguraciju"
          },
          "action-editor": {
            "navigation_path": "Navigation Path",
            "url_path": "URL Path",
            "editor_service_data": "Service data can only be entered in the code editor",
            "actions": {
              "default_action": "Default Action",
              "call-service": "Call Service",
              "more-info": "More Info",
              "toggle": "Toggle",
              "navigate": "Navigate",
              "url": "URL",
              "none": "No Action"
            }
          },
          "card": {
            "alarm-panel": {
              "name": "Alarm Panel",
              "available_states": "Available States",
              "description": "The Alarm Panel card allows you to Arm and Disarm your alarm control panel integrations."
            },
            "calendar": {
              "name": "Calendar",
              "description": "The Calendar card displays a calendar including day, week and list views",
              "inital_view": "Initial View",
              "calendar_entities": "Calendar Entities",
              "views": {
                "dayGridMonth": "Month",
                "dayGridDay": "Day",
                "listWeek": "List"
              }
            },
            "conditional": {
              "name": "Conditional",
              "description": "The Conditional card displays another card based on entity states.",
              "conditions": "Conditions",
              "card": "Card",
              "state_equal": "State is equal to",
              "state_not_equal": "State is not equal to",
              "current_state": "current",
              "condition_explanation": "The card will be shown when ALL conditions below are fulfilled.",
              "change_type": "Change type"
            },
            "config": { "required": "Potreban", "optional": "Neobavezno" },
            "entities": {
              "name": "Entities",
              "show_header_toggle": "Prikaži glavni prekidač?",
              "toggle": "Toggle entities.",
              "description": "The Entities card is the most common type of card. It groups items together into lists.",
              "special_row": "special row",
              "edit_special_row": "View the details of this row by clicking the edit button",
              "entity_row_editor": "Entity Row Editor",
              "secondary_info_values": {
                "none": "No Secondary Info",
                "entity-id": "Entity ID",
                "last-changed": "Last Changed",
                "last-triggered": "Last Triggered",
                "position": "Position",
                "tilt-position": "Tilt Position",
                "brightness": "Brightness",
                "last-updated": "Last Updated"
              },
              "entity_row": {
                "divider": "Divider",
                "call-service": "Call Service",
                "section": "Section",
                "weblink": "Web Link",
                "attribute": "Attribute",
                "buttons": "Buttons",
                "conditional": "Conditional",
                "cast": "Cast",
                "button": "Button"
              }
            },
            "entity": {
              "name": "Entity",
              "description": "The Entity card gives you a quick overview of your entity’s state."
            },
            "button": {
              "name": "Button",
              "description": "The Button card allows you to add buttons to perform tasks.",
              "default_action_help": "The default action depends on the entity's capabilities, it will either be toggled or the more info will be shown."
            },
            "entity-filter": {
              "name": "Entity Filter",
              "description": "The Entity Filter card allows you to define a list of entities that you want to track only when in a certain state."
            },
            "gauge": {
              "name": "Gauge",
              "severity": {
                "define": "Definiraj ozbiljnost?",
                "green": "Zelena",
                "red": "Crvena",
                "yellow": "Žuta"
              },
              "description": "The Gauge card is a basic card that allows visually seeing sensor data."
            },
            "glance": {
              "name": "Glance",
              "columns": "Stupci",
              "description": "The Glance card is useful to group multiple sensors in a compact overview."
            },
            "grid": {
              "name": "Grid",
              "description": "The Grid card allows you to show multiple cards in a grid."
            },
            "logbook": {
              "name": "Logbook",
              "description": "The Logbook card shows a list of events for entities."
            },
            "history-graph": {
              "name": "History Graph",
              "description": "The History Graph card allows you to display a graph for each of the entities listed."
            },
            "horizontal-stack": {
              "name": "Horizontal Stack",
              "description": "The Horizontal Stack card allows you to stack together multiple cards, so they always sit next to each other in the space of one column."
            },
            "humidifier": {
              "name": "Humidifier",
              "description": "The Humidifier card gives control of your humidifier entity. Allowing you to change the humidity and mode of the entity."
            },
            "iframe": {
              "name": "Webpage",
              "description": "The Webpage card allows you to embed your favorite webpage right into Home Assistant."
            },
            "light": {
              "name": "Light",
              "description": "The Light card allows you to change the brightness of the light."
            },
            "generic": {
              "aspect_ratio": "Omjer",
              "attribute": "Attribute",
              "camera_image": "Entitet kamere",
              "camera_view": "Prikaz kamere",
              "double_tap_action": "Double Tap Action",
              "entities": "Entiteti",
              "entity": "Entitet",
              "hold_action": "Radnja pri držanju",
              "hours_to_show": "Sati za prikazivanje",
              "icon": "Ikona",
              "icon_height": "Visina ikone",
              "image": "Putanja slike",
              "maximum": "Maksimum",
              "manual": "Manual",
              "manual_description": "Need to add a custom card or just want to manually write the yaml?",
              "minimum": "Minimum",
              "name": "Ime",
              "refresh_interval": "Interval ažuriranja",
              "show_icon": "Prikaži ikonu?",
              "show_name": "Prikaži ime?",
              "show_state": "Prikaži stanje?",
              "tap_action": "Radnja pri dodiru",
              "title": "Naslov",
              "theme": "Tema",
              "no_theme": "No theme",
              "unit": "Jedinica",
              "url": "URL",
              "state": "State",
              "secondary_info_attribute": "Secondary Info Attribute",
              "search": "Search",
              "state_color": "Color icons based on state?"
            },
            "map": {
              "name": "Map",
              "geo_location_sources": "Izvori geolokacije",
              "dark_mode": "Tamni način?",
              "default_zoom": "Zadano zumiranje",
              "hours_to_show": "Hours to Show",
              "source": "Izvor",
              "description": "The Map card that allows you to display entities on a map."
            },
            "markdown": {
              "name": "Markdown",
              "content": "Sadržaj",
              "description": "The Markdown card is used to render Markdown."
            },
            "media-control": {
              "name": "Media Control",
              "description": "The Media Control card is used to display media player entities on an interface with easy to use controls."
            },
            "picture": {
              "name": "Picture",
              "description": "The Picture card allows you to set an image to use for navigation to various paths in your interface or to call a service."
            },
            "picture-elements": {
              "name": "Picture Elements",
              "description": "The Picture Elements card is one of the most versatile types of cards. The cards allow you to position icons or text and even services! On an image based on coordinates."
            },
            "picture-entity": {
              "name": "Picture Entity",
              "description": "The Picture Entity card displays an entity in the form of an image. Instead of images from URL, it can also show the picture of camera entities."
            },
            "picture-glance": {
              "name": "Picture Glance",
              "description": "The Picture Glance card shows an image and corresponding entity states as an icon. The entities on the right side allow toggle actions, others show the more information dialog."
            },
            "plant-status": {
              "name": "Plant Status",
              "description": "The Plant Status card is for all the lovely botanists out there."
            },
            "sensor": {
              "name": "Sensor",
              "show_more_detail": "Show more detail",
              "graph_type": "Vrsta grafikona",
              "description": "The Sensor card gives you a quick overview of your sensors state with an optional graph to visualize change over time.",
              "graph_detail": "Detalj grafikona"
            },
            "shopping-list": {
              "name": "Shopping List",
              "description": "The Shopping List card allows you to add, edit, check-off, and clear items from your shopping list.",
              "integration_not_loaded": "Ova kartica zahtijeva postavljanje integracije `shopping_list`."
            },
            "thermostat": {
              "name": "Thermostat",
              "description": "The Thermostat card gives control of your climate entity. Allowing you to change the temperature and mode of the entity."
            },
            "vertical-stack": {
              "name": "Vertical Stack",
              "description": "The Vertical Stack card allows you to group multiple cards so they always sit in the same column."
            },
            "weather-forecast": {
              "name": "Weather Forecast",
              "description": "The Weather Forecast card displays the weather. Very useful to include on interfaces that people display on the wall.",
              "show_forecast": "Show Forecast"
            }
          },
          "view": {
            "panel_mode": {
              "title": "Panel Mode?",
              "description": "This renders the first card at full width. Other cards in this view as well as badges will not be rendered.",
              "warning_multiple_cards": "This view contains more than one card, but a panel view can only show 1 card."
            }
          },
          "cardpicker": {
            "no_description": "No description available.",
            "custom_card": "Custom",
            "domain": "Domain",
            "entity": "Entity",
            "by_entity": "By Entity",
            "by_card": "By Card"
          },
          "header-footer": {
            "header": "Header",
            "footer": "Footer",
            "choose_header_footer": "Choose a {type}",
            "types": {
              "graph": { "name": "Graph" },
              "picture": { "name": "Picture" },
              "buttons": { "name": "Buttons" }
            }
          },
          "sub-element-editor": {
            "types": {
              "header": "Header Editor",
              "footer": "Footer Editor",
              "row": "Entity Row Editor"
            }
          }
        },
        "warning": {
          "attribute_not_found": "Attribute {attribute} not available in: {entity}",
          "entity_not_found": "Entitet nije dostupan: {entity}",
          "entity_non_numeric": "Entitet nije numerički: {entity}",
          "entity_unavailable": "{entity} is currently unavailable",
          "starting": "Home Assistant is starting, not everything may be available yet"
        },
        "changed_toast": {
          "message": "Konfiguracija Lovelace je ažurirana, želite li je osvježiti?",
          "refresh": "Osvježi"
        },
        "reload_lovelace": "Ponovo učitajte Lovelace"
      },
      "shopping_list": { "start_conversation": "Start conversation" },
      "custom": {
        "external_panel": {
          "question_trust": "Vjerujete li vanjskom panelu {name} na {link}?",
          "complete_access": "Imat će pristup svim podacima u Home Assistantu.",
          "hide_message": "Provjerite dokumentaciju za komponentu panel_custom kako biste sakrili ovu poruku"
        }
      }
    }
  }
}
